{
 "sections": [
  {
   "id": "0e940b79-8d02-b4f6-66b1-b28b94157920",
   "title": "Multiple Activities and Intents",
   "files": [],
   "layout": "1-panel",
   "path": [],
   "type": "markdown",
   "content-file": ".guides/content/Multiple-Activities-and-Intents-0e94.md",
   "chapter": true,
   "reset": [],
   "teacherOnly": false
  },
  {
   "id": "83609bc2-d9fd-9a17-0c09-366b81965f03",
   "title": "Steps for App",
   "files": [],
   "path": [],
   "type": "markdown",
   "content-file": ".guides/content/Steps-for-App-8360.md",
   "chapter": false,
   "reset": [],
   "teacherOnly": false
  },
  {
   "id": "d2b4eece-acff-845c-b629-81dab78ff8e5",
   "title": "App Diagram",
   "files": [],
   "path": [],
   "type": "markdown",
   "content-file": ".guides/content/App-Diagram-d2b4.md",
   "chapter": false,
   "reset": [],
   "teacherOnly": false
  },
  {
   "id": "5f4c868a-845a-7318-213f-2892408df53c",
   "title": "Creating the App",
   "files": [],
   "path": [],
   "type": "markdown",
   "content-file": ".guides/content/Creating-the-App-5f4c.md",
   "chapter": false,
   "reset": [],
   "teacherOnly": false
  },
  {
   "id": "d0820ed1-1243-f934-cf54-d03dd7a8ee3e",
   "title": "Multiple Activities",
   "files": [],
   "path": [],
   "type": "markdown",
   "content-file": ".guides/content/Multiple-Activities-d082.md",
   "chapter": false,
   "reset": [],
   "teacherOnly": false
  },
  {
   "id": "a58f9204-d9ed-69e0-bf58-28491dc76050",
   "title": "Create First Activity",
   "files": [],
   "path": [],
   "type": "markdown",
   "content-file": ".guides/content/Create-First-Activity-a58f.md",
   "chapter": false,
   "reset": [],
   "teacherOnly": false
  },
  {
   "id": "9403f510-47e1-3666-a7a7-3604d7adb23d",
   "title": "Code",
   "files": [],
   "path": [],
   "type": "markdown",
   "content-file": ".guides/content/Code-9403.md",
   "chapter": false,
   "reset": [],
   "teacherOnly": false
  },
  {
   "id": "4275b63e-c679-5620-5090-bd0d3fe15c62",
   "title": "< EditText >",
   "files": [],
   "path": [],
   "type": "markdown",
   "content-file": ".guides/content/--EditText---4275.md",
   "chapter": false,
   "reset": [],
   "teacherOnly": false
  },
  {
   "id": "0f12d9df-e460-99ce-0305-8a311592fb40",
   "title": "Edit strings.xml",
   "files": [],
   "path": [],
   "type": "markdown",
   "content-file": ".guides/content/Edit-strings-xml-0f12.md",
   "chapter": false,
   "reset": [],
   "teacherOnly": false
  },
  {
   "id": "c12cabd6-aaa7-472c-3e52-37d8437d2b6d",
   "title": "Add onSendMessage() Method",
   "files": [],
   "path": [],
   "type": "markdown",
   "content-file": ".guides/content/Add-onSendMessage---Method-c12c.md",
   "chapter": false,
   "reset": [],
   "teacherOnly": false
  },
  {
   "id": "531b3df1-5dab-792a-dfb7-fb8aeceed352",
   "title": "Create Second Activity",
   "files": [],
   "path": [],
   "type": "markdown",
   "content-file": ".guides/content/Create-Second-Activity-531b.md",
   "chapter": false,
   "reset": [],
   "teacherOnly": false
  },
  {
   "id": "5f6b0086-b82c-a053-77a7-458162f6abe9",
   "title": "Second Activity",
   "files": [],
   "path": [],
   "type": "markdown",
   "content-file": ".guides/content/Second-Activity-5f6b.md",
   "chapter": false,
   "reset": [],
   "teacherOnly": false
  },
  {
   "id": "428ed789-69a1-c975-4135-31fb0b34f6c7",
   "title": "Android Manifest",
   "files": [],
   "path": [],
   "type": "markdown",
   "content-file": ".guides/content/Android-Manifest-428e.md",
   "chapter": false,
   "reset": [],
   "teacherOnly": false
  },
  {
   "id": "14df8f3d-cd6a-fb69-b092-466a1e30177f",
   "title": "Activity Elements",
   "files": [],
   "path": [],
   "type": "markdown",
   "content-file": ".guides/content/Activity-Elements-14df.md",
   "chapter": false,
   "reset": [],
   "teacherOnly": false
  },
  {
   "id": "2a04ee14-33e0-82e1-c3f4-74cfc3739804",
   "title": "Create an Intent",
   "files": [],
   "path": [],
   "type": "markdown",
   "content-file": ".guides/content/Create-an-Intent-2a04.md",
   "chapter": false,
   "reset": [],
   "teacherOnly": false
  },
  {
   "id": "7720e17e-45b5-80f6-2dc5-381f9b78cd11",
   "title": "Starting Activity",
   "files": [],
   "path": [],
   "type": "markdown",
   "content-file": ".guides/content/Starting-Activity-7720.md",
   "chapter": false,
   "reset": [],
   "teacherOnly": false
  },
  {
   "id": "c93010c1-664d-f801-69cd-552e5b9d4da4",
   "title": "Use an Intent",
   "files": [],
   "path": [],
   "type": "markdown",
   "content-file": ".guides/content/Use-an-Intent-c930.md",
   "chapter": false,
   "reset": [],
   "teacherOnly": false
  },
  {
   "id": "1f35f5cf-00d9-e4f3-fae1-3e299c163cf6",
   "title": "App Flow",
   "files": [],
   "path": [],
   "type": "markdown",
   "content-file": ".guides/content/App-Flow-1f35.md",
   "chapter": false,
   "reset": [],
   "teacherOnly": false
  },
  {
   "id": "be0ce6c8-acbd-32cc-5f97-d42816a3ea37",
   "title": "What the User Sees",
   "files": [],
   "path": [],
   "type": "markdown",
   "content-file": ".guides/content/What-the-User-Sees-be0c.md",
   "chapter": false,
   "reset": [],
   "teacherOnly": false
  },
  {
   "id": "2683be59-a60a-a386-b5a3-2bfe19f8823a",
   "title": "Recap and Next Steps",
   "files": [],
   "path": [],
   "type": "markdown",
   "content-file": ".guides/content/Recap-and-Next-Steps-2683.md",
   "chapter": false,
   "reset": [],
   "teacherOnly": false
  },
  {
   "id": "02e483d7-2005-61a6-ac7a-39a68d1de9f7",
   "title": "Layout Changes",
   "files": [],
   "path": [],
   "type": "markdown",
   "content-file": ".guides/content/Layout-Changes-02e4.md",
   "chapter": false,
   "reset": [],
   "teacherOnly": false
  },
  {
   "id": "4348e8de-2910-932e-75c5-d1a08363a623",
   "title": "Pass Data - Send Data",
   "files": [],
   "path": [],
   "type": "markdown",
   "content-file": ".guides/content/Pass-Data---Send-Data-4348.md",
   "chapter": false,
   "reset": [],
   "teacherOnly": false
  },
  {
   "id": "59981c51-bcf2-edde-19d8-16adc861ed73",
   "title": "Pass Data - Receive Data",
   "files": [],
   "path": [],
   "type": "markdown",
   "content-file": ".guides/content/Pass-Data---Receive-Data-5998.md",
   "chapter": false,
   "reset": [],
   "teacherOnly": false
  },
  {
   "id": "300c1479-bb12-ce78-d00c-1b46cff686f1",
   "title": "Update Code",
   "files": [],
   "path": [],
   "type": "markdown",
   "content-file": ".guides/content/Update-Code-300c.md",
   "chapter": false,
   "reset": [],
   "teacherOnly": false
  },
  {
   "id": "9930a24d-a1a2-ae69-29e1-2da632e777a8",
   "title": "Updates",
   "files": [],
   "path": [],
   "type": "markdown",
   "content-file": ".guides/content/Updates-9930.md",
   "chapter": false,
   "reset": [],
   "teacherOnly": false
  },
  {
   "id": "ac944a91-8530-d99e-084c-97d9730a207e",
   "title": "Multiple Activities - Recap",
   "files": [],
   "path": [],
   "type": "markdown",
   "content-file": ".guides/content/Multiple-Activities---Recap-ac94.md",
   "chapter": false,
   "reset": [],
   "teacherOnly": false
  },
  {
   "id": "f375f8c8-f1f7-7daf-1938-35e4d9f3f7f2",
   "title": "Recap",
   "files": [],
   "path": [],
   "type": "markdown",
   "content-file": ".guides/content/Recap-f375.md",
   "chapter": false,
   "reset": [],
   "teacherOnly": false
  }
 ],
 "theme": "light",
 "scripts": [],
 "lexikonTopic": ""
}